aajna/__init__.py
aajna/device.py
aajna/vis/__init__.py
aajna/vis/three.py
aajna-0.0.8.dist-info/LICENSE
aajna-0.0.8.dist-info/METADATA
aajna-0.0.8.dist-info/WHEEL
aajna-0.0.8.dist-info/top_level.txt
aajna-0.0.8.dist-info/RECORD
