Metadata-Version: 2.1
Name: aajna
Version: 0.0.8
Summary: A high level library for mechanistic interpretability.
Home-page: https://github.com/33-Papers/aajna
Author: Mridul Sharma
Author-email: mridulsharma3301@gmail.com
Classifier: Natural Language :: English
Classifier: License :: OSI Approved :: MIT License
Classifier: Operating System :: OS Independent
License-File: LICENSE
Requires-Dist: torch
Requires-Dist: matplotlib
Requires-Dist: importlib-metadata ; python_version < "3.13"
